cloudflare_images_migrator-1.0.1.dist-info/licenses/LICENSE
src/__init__.py
src/audit.py
src/cloudflare_client.py
src/config.py
src/image_tracker.py
src/logger.py
src/migrator.py
src/parsers.py
src/quality.py
src/security.py
src/utils.py
cloudflare_images_migrator-1.0.1.dist-info/METADATA
cloudflare_images_migrator-1.0.1.dist-info/WHEEL
cloudflare_images_migrator-1.0.1.dist-info/entry_points.txt
cloudflare_images_migrator-1.0.1.dist-info/top_level.txt
cloudflare_images_migrator-1.0.1.dist-info/RECORD
