Metadata-Version: 2.4
Name: cloudflare-images-migrator
Version: 1.0.1
Summary: Enterprise-grade tool to migrate images to Cloudflare Images with persistent tracking and duplicate detection
Home-page: https://github.com/mariolqn/Cloudflare-Images-Migrator
Author: Mario Lemos Quirino Neto
Author-email: Mario Lemos Quirino Neto <mariolqn@users.noreply.github.com>
License: MIT
Project-URL: Homepage, https://github.com/mariolqn/Cloudflare-Images-Migrator
Project-URL: Bug Tracker, https://github.com/mariolqn/Cloudflare-Images-Migrator/issues
Project-URL: Documentation, https://github.com/mariolqn/Cloudflare-Images-Migrator#readme
Project-URL: Source Code, https://github.com/mariolqn/Cloudflare-Images-Migrator
Keywords: cloudflare,images,migration,cdn,optimization,duplicate-detection,enterprise,security,tracking,automation
Classifier: Development Status :: 5 - Production/Stable
Classifier: Intended Audience :: Developers
Classifier: Topic :: Internet :: WWW/HTTP
Classifier: Topic :: Multimedia :: Graphics
Classifier: Topic :: Software Development :: Libraries :: Python Modules
Classifier: Topic :: System :: Archiving :: Backup
Classifier: License :: OSI Approved :: MIT License
Classifier: Programming Language :: Python :: 3
Classifier: Programming Language :: Python :: 3.8
Classifier: Programming Language :: Python :: 3.9
Classifier: Programming Language :: Python :: 3.10
Classifier: Programming Language :: Python :: 3.11
Classifier: Programming Language :: Python :: 3.12
Classifier: Operating System :: OS Independent
Classifier: Environment :: Console
Requires-Python: >=3.8
License-File: LICENSE
Requires-Dist: requests>=2.28.0
Requires-Dist: pillow>=9.0.0
Requires-Dist: tqdm>=4.64.0
Requires-Dist: colorama>=0.4.4
Requires-Dist: pyyaml>=6.0
Requires-Dist: python-magic>=0.4.24
Requires-Dist: beautifulsoup4>=4.11.0
Requires-Dist: python-dotenv>=0.19.0
Provides-Extra: dev
Requires-Dist: pytest>=6.0; extra == "dev"
Requires-Dist: pytest-cov; extra == "dev"
Requires-Dist: black; extra == "dev"
Requires-Dist: flake8; extra == "dev"
Requires-Dist: mypy; extra == "dev"
Dynamic: author
Dynamic: home-page
Dynamic: license-file
Dynamic: requires-python
